negmas_elicit/__init__.py
negmas_elicit/base.py
negmas_elicit/baseline.py
negmas_elicit/common.py
negmas_elicit/expectors.py
negmas_elicit/mechanism.py
negmas_elicit/pandora.py
negmas_elicit/py.typed
negmas_elicit/queries.py
negmas_elicit/strategy.py
negmas_elicit/user.py
negmas_elicit/voi.py
negmas_elicit-0.1.1.dist-info/METADATA
negmas_elicit-0.1.1.dist-info/WHEEL
negmas_elicit-0.1.1.dist-info/licenses/LICENSE
negmas_elicit-0.1.1.dist-info/RECORD
