Metadata-Version: 2.4
Name: negmas-elicit
Version: 0.1.1
Summary: Preference elicitation module for automated negotiation, extracted from the NegMAS library
Project-URL: Homepage, https://github.com/yasserfarouk/negmas-elicit
Project-URL: Documentation, https://yasserfarouk.github.io/negmas-elicit
Project-URL: Repository, https://github.com/yasserfarouk/negmas-elicit
Project-URL: Issues, https://github.com/yasserfarouk/negmas-elicit/issues
Author-email: Yasser Mohammad <yasserfarouk@gmail.com>
License-Expression: AGPL-3.0-or-later
License-File: LICENSE
Keywords: automated-negotiation,multi-agent-systems,negmas,negotiation,preference-elicitation
Classifier: Development Status :: 4 - Beta
Classifier: Intended Audience :: Developers
Classifier: Intended Audience :: Science/Research
Classifier: License :: OSI Approved :: GNU Affero General Public License v3 or later (AGPLv3+)
Classifier: Operating System :: OS Independent
Classifier: Programming Language :: Python :: 3
Classifier: Programming Language :: Python :: 3.12
Classifier: Programming Language :: Python :: 3.13
Classifier: Topic :: Scientific/Engineering :: Artificial Intelligence
Classifier: Typing :: Typed
Requires-Python: >=3.12
Requires-Dist: negmas>=0.10.0
Requires-Dist: sortedcontainers>=2.4.0
